stability_matrix_tools/__init__.py
stability_matrix_tools/b2.py
stability_matrix_tools/cf.py
stability_matrix_tools/config.py
stability_matrix_tools/git.py
stability_matrix_tools/keys.py
stability_matrix_tools/main.py
stability_matrix_tools/models/__init__.py
stability_matrix_tools/models/keyring_config.py
stability_matrix_tools/models/settings.py
stability_matrix_tools/models/update_base.py
stability_matrix_tools/models/update_info.py
stability_matrix_tools/models/update_info_v3.py
stability_matrix_tools/models/version.py
stability_matrix_tools/updates.py
stability_matrix_tools/utils/__init__.py
stability_matrix_tools/utils/cf_cache.py
stability_matrix_tools/utils/changelog_parser.py
stability_matrix_tools/utils/console_diff.py
stability_matrix_tools/utils/git_process.py
stability_matrix_tools/utils/name_converter.py
stability_matrix_tools/utils/progress.py
stability_matrix_tools/utils/signing.py
stability_matrix_tools/utils/spinners.py
stability_matrix_tools/utils/stream_hash.py
stability_matrix_tools/utils/uploader.py
stability_matrix_tools/utils/uris.py
stability_matrix_tools-0.3.3.dist-info/entry_points.txt
stability_matrix_tools-0.3.3.dist-info/LICENSE
stability_matrix_tools-0.3.3.dist-info/METADATA
stability_matrix_tools-0.3.3.dist-info/WHEEL
stability_matrix_tools-0.3.3.dist-info/RECORD
