Metadata-Version: 2.1
Name: stability-matrix-tools
Version: 0.3.3
Summary: 
Author: Ionite
Author-email: dev@ionite.io
Requires-Python: >=3.10,<3.13
Classifier: Programming Language :: Python :: 3
Classifier: Programming Language :: Python :: 3.10
Classifier: Programming Language :: Python :: 3.11
Classifier: Programming Language :: Python :: 3.12
Requires-Dist: b2sdk (>=2.5.1,<3.0.0)
Requires-Dist: blake3 (>=0.4.1,<0.5.0)
Requires-Dist: cryptography (>=43.0.1,<44.0.0)
Requires-Dist: httpx (>=0.27.2,<0.28.0)
Requires-Dist: keyring (>=25.4.0,<26.0.0)
Requires-Dist: pydantic[dotenv] (>=2.4.2,<3.0.0)
Requires-Dist: pygithub (>=2.1.1,<3.0.0)
Requires-Dist: pyperclip (>=1.8.2,<2.0.0)
Requires-Dist: python-dotenv (>=1.0.0,<2.0.0)
Requires-Dist: semver (>=3.0.2,<4.0.0)
Requires-Dist: typer[all] (>=0.12.5,<0.13.0)
Requires-Dist: yaspin (>=3.0.1,<4.0.0)
